kubespawner/__init__.py
kubespawner/clients.py
kubespawner/objects.py
kubespawner/proxy.py
kubespawner/reflector.py
kubespawner/spawner.py
kubespawner/traitlets.py
kubespawner/utils.py
rubin_kubespawner-2.0.1.dev6.dist-info/LICENSE
rubin_kubespawner-2.0.1.dev6.dist-info/METADATA
rubin_kubespawner-2.0.1.dev6.dist-info/WHEEL
rubin_kubespawner-2.0.1.dev6.dist-info/top_level.txt
rubin_kubespawner-2.0.1.dev6.dist-info/RECORD
