Metadata-Version: 2.1
Name: rubin-kubespawner
Version: 2.0.1.dev6
Summary: JupyterHub Spawner for Kubernetes (Rubin asyncio version)
Home-page: http://github.com/lsst-sqre/kubespawner
Author: Jupyter Contributors
Author-email: jupyter@googlegroups.com
License: BSD
Project-URL: Documentation, https://jupyterhub-kubespawner.readthedocs.io
Project-URL: Source, https://github.com/jupyterhub/kubespawner
Project-URL: Tracker, https://github.com/jupyterhub/kubespawner/issues
Platform: UNKNOWN
Requires-Python: >=3.7
License-File: LICENSE
Requires-Dist: async-generator (>=1.8)
Requires-Dist: escapism
Requires-Dist: python-slugify
Requires-Dist: jupyterhub (>=0.8)
Requires-Dist: jinja2
Requires-Dist: kubernetes-asyncio (>=19.15.1)
Requires-Dist: urllib3
Requires-Dist: pyYAML
Provides-Extra: test
Requires-Dist: bump2version ; extra == 'test'
Requires-Dist: flake8 ; extra == 'test'
Requires-Dist: kubernetes (>=10.1.0) ; extra == 'test'
Requires-Dist: pytest (>=5.4) ; extra == 'test'
Requires-Dist: pytest-cov ; extra == 'test'
Requires-Dist: pytest-asyncio (>=0.11.0) ; extra == 'test'
